[
  {
    "name": "Baardegem",
    "gpxLink": "assets/gpx/Baardegem.gpx",
    "afspraakDatum": "2024-11-17T08:30:00Z"
  },
  {
    "name": "Koningshooikt",
    "gpxLink": "assets/gpx/Koningshooikt.gpx",
    "afspraakDatum": "2024-11-10T08:30:00Z"
  },
  {
    "name": "Fort van Borsbeek",
    "gpxLink": "assets/gpx/Fort van Borsbeek.gpx",
    "afspraakDatum": "2024-11-03T08:30:00Z"
  },
  {
    "name": "Rondom Leuven",
    "gpxLink": "assets/gpx/Rondom Leuven.gpx",
    "afspraakDatum": "2024-10-27T08:30:00Z"
  },
  {
    "name": "Mazenzele",
    "gpxLink": "assets/gpx/Mazenzele.gpx",
    "afspraakDatum": "2024-10-27T08:30:00Z"
  }
]
